__init__.py
lab.py
pyqtwidgetlab-1.0.0.dist-info/METADATA
pyqtwidgetlab-1.0.0.dist-info/WHEEL
pyqtwidgetlab-1.0.0.dist-info/top_level.txt
pyqtwidgetlab-1.0.0.dist-info/RECORD
