Metadata-Version: 2.4
Name: pyqtwidgetlab
Version: 1.0.0
Summary: An example project including all of the most used PyQt on a basic window.
Author-email: Daniel Dunal <robindunal@gmail.com>
License: MIT
Requires-Python: >=3.8
Requires-Dist: PyQt6>=6.5
